desktop_groups/__init__.py
desktop_groups/__main__.py
desktop_groups/group.py
desktop_groups/gui.py
desktop_groups/assets/img/desktopgroups256px.ico
desktop_groups/assets/json/desktopgroups.schema.json
desktop_groups/assets/lang/de.json
desktop_groups/assets/lang/en.json
desktop_groups/assets/lang/fr.json
desktop_groups-0.0.4.dist-info/LICENSE
desktop_groups-0.0.4.dist-info/METADATA
desktop_groups-0.0.4.dist-info/WHEEL
desktop_groups-0.0.4.dist-info/entry_points.txt
desktop_groups-0.0.4.dist-info/top_level.txt
desktop_groups-0.0.4.dist-info/RECORD
