Metadata-Version: 2.1
Name: desktop-groups
Version: 0.0.4
Summary: Organizes your desktop
Author: Nitro4542
Project-URL: Homepage, https://github.com/Nitro4542/desktop-groups
Project-URL: Issues, https://github.com/Nitro4542/desktop-groups/issues
Classifier: Programming Language :: Python :: 3
Classifier: License :: OSI Approved :: The Unlicense (Unlicense)
Classifier: Operating System :: OS Independent
Requires-Python: >=3.10
License-File: LICENSE
Requires-Dist: customtkinter
Requires-Dist: pillow
Requires-Dist: jsonschema
Requires-Dist: argparse
Requires-Dist: icoextract
